zephyrflow/__init__.py
zephyrflow/core/__init__.py
zephyrflow/core/base.py
zephyrflow/core/consumers.py
zephyrflow/core/factory.py
zephyrflow/core/retry.py
zephyrflow/examples/__init__.py
zephyrflow/examples/kafka_example.py
zephyrflow/examples/mixed_clients_example.py
zephyrflow/examples/rabbitmq_example.py
zephyrflow/examples/redis_example.py
zephyrflow/kafka/__init__.py
zephyrflow/kafka/async_client.py
zephyrflow/kafka/sync_client.py
zephyrflow/rabbit/__init__.py
zephyrflow/rabbit/async_client.py
zephyrflow/rabbit/sync_client.py
zephyrflow/redis/__init__.py
zephyrflow/redis/async_client.py
zephyrflow/redis/sync_client.py
zephyrflow/testing/__init__.py
zephyrflow/testing/helpers.py
zephyrflow/testing/mock_client.py
zephyrflow-0.2.0.dist-info/LICENSE
zephyrflow-0.2.0.dist-info/METADATA
zephyrflow-0.2.0.dist-info/WHEEL
zephyrflow-0.2.0.dist-info/RECORD
