Metadata-Version: 2.1
Name: zephyrflow
Version: 0.2.0
Summary: A messaging library supporting multiple backends
Author: Zbigniew Mastylo
Author-email: z.mastylo@protonmail.com
Requires-Python: >=3.9,<4.0
Classifier: Programming Language :: Python :: 3
Classifier: Programming Language :: Python :: 3.9
Classifier: Programming Language :: Python :: 3.10
Classifier: Programming Language :: Python :: 3.11
Classifier: Programming Language :: Python :: 3.12
Requires-Dist: aio-pika (>=9.3.1,<10.0.0)
Requires-Dist: aiokafka (>=0.10.0,<0.11.0)
Requires-Dist: kafka-python (>=2.0.2,<3.0.0)
Requires-Dist: pika (>=1.3.2,<2.0.0)
Requires-Dist: redis[hiredis] (>=5.0.1,<6.0.0)
Requires-Dist: types-redis (>=4.6.0.20241004,<5.0.0.0)
